micropython_isl29125/__init__.py
micropython_isl29125/i2c_helpers.py
micropython_isl29125/isl29125.py
micropython_isl29125-0.1.2.dist-info/LICENSE
micropython_isl29125-0.1.2.dist-info/METADATA
micropython_isl29125-0.1.2.dist-info/WHEEL
micropython_isl29125-0.1.2.dist-info/top_level.txt
micropython_isl29125-0.1.2.dist-info/RECORD
