Metadata-Version: 2.1
Name: micropython-isl29125
Version: 0.1.2
Summary: MicroPython Driver for the Intersil ISL29125 Color Sensor
Author-email: JDM <xxyx@mailmeto.mozmail.com>
License: MIT
Project-URL: Homepage, https://github.com/jposada202020/MicroPython_ISL29125
Keywords: sensor,micropython,color,sensor,intersil,RGB,isl29125
Classifier: Intended Audience :: Developers
Classifier: Topic :: Software Development :: Libraries
Classifier: Topic :: Software Development :: Embedded Systems
Classifier: Topic :: System :: Hardware
Classifier: License :: OSI Approved :: MIT License
Classifier: Programming Language :: Python :: Implementation :: MicroPython
License-File: LICENSE
